LICENSE
MANIFEST.in
README.mkd
requirements.txt
setup.py
pydelaunator/__init__.py
pydelaunator/__main__.py
pydelaunator/commons.py
pydelaunator/edge.py
pydelaunator/face.py
pydelaunator/geometry.py
pydelaunator/gui.py
pydelaunator/mesh.py
pydelaunator/navigation.py
pydelaunator/placer.py
pydelaunator/setup_logging.py
pydelaunator/vertex.py
pydelaunator.egg-info/PKG-INFO
pydelaunator.egg-info/SOURCES.txt
pydelaunator.egg-info/dependency_links.txt
pydelaunator.egg-info/requires.txt
pydelaunator.egg-info/top_level.txt
pydelaunator/test/__init__.py
pydelaunator/test/stress_test.py
pydelaunator/test/test_geometry.py
pydelaunator/test/test_mesh.py
pydelaunator/test/test_placer.py