Metadata-Version: 1.1
Name: pydelaunator
Version: 0.0.12
Summary: quad-edge data structure
Home-page: https://github.com/Aluriak/pydelaunator
Author: lucas bourneuf
Author-email: lucas.bourneuf@openmailbox.org
License: UNKNOWN
Keywords: graph data structure
Platform: UNKNOWN
Classifier: Development Status :: 2 - Pre-Alpha
Classifier: Intended Audience :: Science/Research
Classifier: License :: OSI Approved :: GNU General Public License (GPL)
Classifier: Natural Language :: English
Classifier: Programming Language :: Python :: 3
Classifier: Topic :: Software Development :: Libraries :: Python Modules
